{
  "query": "slippers",
  "search_url": "https://www.myntra.com/slippers?rawQuery=slippers",
  "total_products": 3,
  "products": [
    {
      "name": "WOLVESDEN",
      "price": "₹389",
      "original_price": "MRP ₹1299",
      "discount": "(70% OFF)",
      "brand": "",
      "category": "More By WOLVESDEN",
      "rating": "5",
      "reviews_count": "",
      "size_options": [
        "5",
        "8",
        "4",
        "6",
        "7"
      ],
      "color_options": [],
      "availability": "",
      "link": "https://www.myntra.com/flip-flops/wolvesden/wolvesden-women-pack-of-2-fur-room-slippers/35144016/buy",
      "images": [
        {
          "url": "https://constant.myntassets.com/web/assets/img/chevron-right.svg",
          "alt": "",
          "thumbnail": "https://constant.myntassets.com/web/assets/img/chevron-right.svg"
        }
      ],
      "description": "WOLVESDEN\nWomen Pack of 2 Fur Room Slippers\n3.5\n|\n83 Ratings\n₹389\nMRP ₹1299(70% OFF)\ninclusive of all taxes\nSELECT SIZE (UK Size)SIZE CHART\n4\n5\n6\n7\n8\nADD TO BAG\nWISHLIST\nDELIVERY OPTIONS\nPlease enter PIN code to check delivery time & Pay on Delivery Availability\n100% Original Products\nPay on delivery might be available\nEasy 7 days returns and exchanges\nBEST OFFERS\nBest Price: Rs. 311\nApplicable on: Orders above Rs. 300 (only on first purchase)\nCoupon code: BFFSAVE\nCoupon Discount: 20% off (Your total saving: Rs. 988)\nView Eligible Products\n10% Discount on HDFC Bank Credit Card.\nMin Spend ₹750, Max Discount ₹3,500.\nTerms & Condition\n10% Discount on HDFC Bank Credit Card.\nMin Spend ₹1,000, Max Discount ₹3,500.\nTerms & Condition\n10% Discount on HDFC Bank Credit Card EMI.\nMin Spend ₹1,000, Max Discount ₹3,500.\nTerms & Condition\n10% Discount on HDFC Bank Debit Card EMI.\nMin Spend ₹1,000, Max Discount ₹3,500.\nTerms & Condition\nCustomers will receive Rs 250 voucher on a minimum spends of Rs 4,000 made via HDFC Bank NetBanking during Myntra’s BFF sale.\nMin Spend ₹4,000\nTerms & Condition\n7.5% Assured Cashback on Flipkart Axis Bank Credit Card.\nMaximum cashback: INR 4,000 per quarter ; Cashback is not applicable on transactions less than INR 100\nTerms & Condition\n7.5% Assured Cashback on Flipkart SBI Credit Card.\nMaximum cashback: INR 4,000 per quarter ; Cashback is not applicable on transactions less than INR 100\nTerms & Condition\nPRODUCT DETAILS\nA pair of khaki and white embellished room slippers\nFur upper\nCushioned footbed\nPatterned tpr outsole\nMaterial & Care\nUpper material: Fur\nOutsole material: TPR\nWipe with a clean, dry cloth to remove the dust\nSpecifications\nMaterials\nFur\nNet Quantity\n1\nNet Quantity Unit\nPieces\nOccasions\nCasual\nPatterns\nSelf Design\nSole Material\nTPR\nSustainable\nRegular\nType\nRoom Slippers\nRATINGS\n3.5\n83 Verified Buyers\n5\n42\n4\n9\n3\n5\n2\n4\n1\n23\nCustomer Photos (11)\nCustomer Reviews (12)\n5\nGo for it great product\nAshwinii Andhare9 Aug 2025\n11\n1\nGundu Varsha10 July 2025\n20\n5\nVery nice and soft room slipper .worth of money.\nShivam Soni24 Sept 2025\n00\nView all 12 reviews\nProduct Code: 35144016\nSeller: Badami Enterprise\nView Supplier Information",
      "specifications": {
        "WOLVESDEN\nWomen Pack of 2 Fur Room Slippers\n3.5\n|\n83 Ratings\n₹389\nMRP ₹1299(70% OFF)\ninclusive of all taxes\nSELECT SIZE (UK Size)SIZE CHART\n4\n5\n6\n7\n8\nADD TO BAG\nWISHLIST\nDELIVERY OPTIONS\nPlease enter PIN code to check delivery time & Pay on Delivery Availability\n100% Original Products\nPay on delivery might be available\nEasy 7 days returns and exchanges\nBEST OFFERS\nBest Price": "Rs. 311\nApplicable on: Orders above Rs. 300 (only on first purchase)\nCoupon code: BFFSAVE\nCoupon Discount: 20% off (Your total saving: Rs. 988)\nView Eligible Products\n10% Discount on HDFC Bank Credit Card.\nMin Spend ₹750, Max Discount ₹3,500.\nTerms & Condition\n10% Discount on HDFC Bank Credit Card.\nMin Spend ₹1,000, Max Discount ₹3,500.\nTerms & Condition\n10% Discount on HDFC Bank Credit Card EMI.\nMin Spend ₹1,000, Max Discount ₹3,500.\nTerms & Condition\n10% Discount on HDFC Bank Debit Card EMI.\nMin Spend ₹1,000, Max Discount ₹3,500.\nTerms & Condition\nCustomers will receive Rs 250 voucher on a minimum spends of Rs 4,000 made via HDFC Bank NetBanking during Myntra’s BFF sale.\nMin Spend ₹4,000\nTerms & Condition\n7.5% Assured Cashback on Flipkart Axis Bank Credit Card.\nMaximum cashback: INR 4,000 per quarter ; Cashback is not applicable on transactions less than INR 100\nTerms & Condition\n7.5% Assured Cashback on Flipkart SBI Credit Card.\nMaximum cashback: INR 4,000 per quarter ; Cashback is not applicable on transactions less than INR 100\nTerms & Condition\nPRODUCT DETAILS\nA pair of khaki and white embellished room slippers\nFur upper\nCushioned footbed\nPatterned tpr outsole\nMaterial & Care\nUpper material: Fur\nOutsole material: TPR\nWipe with a clean, dry cloth to remove the dust\nSpecifications\nMaterials\nFur\nNet Quantity\n1\nNet Quantity Unit\nPieces\nOccasions\nCasual\nPatterns\nSelf Design\nSole Material\nTPR\nSustainable\nRegular\nType\nRoom Slippers\nRATINGS\n3.5\n83 Verified Buyers\n5\n42\n4\n9\n3\n5\n2\n4\n1\n23\nCustomer Photos (11)\nCustomer Reviews (12)\n5\nGo for it great product\nAshwinii Andhare9 Aug 2025\n11\n1\nGundu Varsha10 July 2025\n20\n5\nVery nice and soft room slipper .worth of money.\nShivam Soni24 Sept 2025\n00\nView all 12 reviews\nProduct Code: 35144016\nSeller: Badami Enterprise\nView Supplier Information",
        "SELECT SIZE (UK Size)SIZE CHART\n4\n5\n6\n7\n8\nADD TO BAG\nWISHLIST\nDELIVERY OPTIONS\nPlease enter PIN code to check delivery time & Pay on Delivery Availability\n100% Original Products\nPay on delivery might be available\nEasy 7 days returns and exchanges\nBEST OFFERS\nBest Price": "Rs. 311\nApplicable on: Orders above Rs. 300 (only on first purchase)\nCoupon code: BFFSAVE\nCoupon Discount: 20% off (Your total saving: Rs. 988)\nView Eligible Products\n10% Discount on HDFC Bank Credit Card.\nMin Spend ₹750, Max Discount ₹3,500.\nTerms & Condition\n10% Discount on HDFC Bank Credit Card.\nMin Spend ₹1,000, Max Discount ₹3,500.\nTerms & Condition\n10% Discount on HDFC Bank Credit Card EMI.\nMin Spend ₹1,000, Max Discount ₹3,500.\nTerms & Condition\n10% Discount on HDFC Bank Debit Card EMI.\nMin Spend ₹1,000, Max Discount ₹3,500.\nTerms & Condition\nCustomers will receive Rs 250 voucher on a minimum spends of Rs 4,000 made via HDFC Bank NetBanking during Myntra’s BFF sale.\nMin Spend ₹4,000\nTerms & Condition\n7.5% Assured Cashback on Flipkart Axis Bank Credit Card.\nMaximum cashback: INR 4,000 per quarter ; Cashback is not applicable on transactions less than INR 100\nTerms & Condition\n7.5% Assured Cashback on Flipkart SBI Credit Card.\nMaximum cashback: INR 4,000 per quarter ; Cashback is not applicable on transactions less than INR 100\nTerms & Condition",
        "BEST OFFERS\nBest Price": "Rs. 311\nApplicable on: Orders above Rs. 300 (only on first purchase)\nCoupon code: BFFSAVE\nCoupon Discount: 20% off (Your total saving: Rs. 988)\nView Eligible Products\n10% Discount on HDFC Bank Credit Card.\nMin Spend ₹750, Max Discount ₹3,500.\nTerms & Condition\n10% Discount on HDFC Bank Credit Card.\nMin Spend ₹1,000, Max Discount ₹3,500.\nTerms & Condition\n10% Discount on HDFC Bank Credit Card EMI.\nMin Spend ₹1,000, Max Discount ₹3,500.\nTerms & Condition\n10% Discount on HDFC Bank Debit Card EMI.\nMin Spend ₹1,000, Max Discount ₹3,500.\nTerms & Condition\nCustomers will receive Rs 250 voucher on a minimum spends of Rs 4,000 made via HDFC Bank NetBanking during Myntra’s BFF sale.\nMin Spend ₹4,000\nTerms & Condition\n7.5% Assured Cashback on Flipkart Axis Bank Credit Card.\nMaximum cashback: INR 4,000 per quarter ; Cashback is not applicable on transactions less than INR 100\nTerms & Condition\n7.5% Assured Cashback on Flipkart SBI Credit Card.\nMaximum cashback: INR 4,000 per quarter ; Cashback is not applicable on transactions less than INR 100\nTerms & Condition",
        "Best Price": "Rs. 311",
        "Applicable on": "Orders above Rs. 300 (only on first purchase)",
        "Coupon code": "BFFSAVE",
        "Coupon Discount": "20% off (Your total saving: Rs. 988)",
        "10% Discount on HDFC Bank Credit Card.\nMin Spend ₹750, Max Discount ₹3,500.\nTerms & Condition\n10% Discount on HDFC Bank Credit Card.\nMin Spend ₹1,000, Max Discount ₹3,500.\nTerms & Condition\n10% Discount on HDFC Bank Credit Card EMI.\nMin Spend ₹1,000, Max Discount ₹3,500.\nTerms & Condition\n10% Discount on HDFC Bank Debit Card EMI.\nMin Spend ₹1,000, Max Discount ₹3,500.\nTerms & Condition\nCustomers will receive Rs 250 voucher on a minimum spends of Rs 4,000 made via HDFC Bank NetBanking during Myntra’s BFF sale.\nMin Spend ₹4,000\nTerms & Condition\n7.5% Assured Cashback on Flipkart Axis Bank Credit Card.\nMaximum cashback": "INR 4,000 per quarter ; Cashback is not applicable on transactions less than INR 100\nTerms & Condition\n7.5% Assured Cashback on Flipkart SBI Credit Card.\nMaximum cashback: INR 4,000 per quarter ; Cashback is not applicable on transactions less than INR 100\nTerms & Condition",
        "7.5% Assured Cashback on Flipkart Axis Bank Credit Card.\nMaximum cashback": "INR 4,000 per quarter ; Cashback is not applicable on transactions less than INR 100\nTerms & Condition",
        "Maximum cashback": "INR 4,000 per quarter ; Cashback is not applicable on transactions less than INR 100",
        "7.5% Assured Cashback on Flipkart SBI Credit Card.\nMaximum cashback": "INR 4,000 per quarter ; Cashback is not applicable on transactions less than INR 100\nTerms & Condition",
        "PRODUCT DETAILS\nA pair of khaki and white embellished room slippers\nFur upper\nCushioned footbed\nPatterned tpr outsole\nMaterial & Care\nUpper material": "Fur\nOutsole material: TPR\nWipe with a clean, dry cloth to remove the dust\nSpecifications\nMaterials\nFur\nNet Quantity\n1\nNet Quantity Unit\nPieces\nOccasions\nCasual\nPatterns\nSelf Design\nSole Material\nTPR\nSustainable\nRegular\nType\nRoom Slippers",
        "Material & Care\nUpper material": "Fur\nOutsole material: TPR\nWipe with a clean, dry cloth to remove the dust",
        "Product Code": "35144016",
        "Seller": "Badami Enterprise\nView Supplier Information"
      }
    },
    {
      "name": "",
      "price": "₹1156",
      "original_price": "MRP ₹1299",
      "discount": "(11% OFF)",
      "brand": "",
      "category": "More By Kappa",
      "rating": "5",
      "reviews_count": "",
      "size_options": [
        "7"
      ],
      "color_options": [],
      "availability": "",
      "link": "https://www.myntra.com/flip-flops/kappa/kappa-men-navy-blue-colourblocked-synthetic-sliders/33376679/buy",
      "images": [
        {
          "url": "https://assets.myntassets.com/f_auto,h_150,q_auto:best,w_112/assets/images/2025/MARCH/28/okSbkIcc_6975fcc48b944954b427e8d53eacf3d3.jpg",
          "alt": "",
          "thumbnail": "https://assets.myntassets.com/f_auto,h_150,q_auto:best,w_112/assets/images/2025/MARCH/28/okSbkIcc_6975fcc48b944954b427e8d53eacf3d3.jpg"
        },
        {
          "url": "https://assets.myntassets.com/f_auto,h_150,q_auto:best,w_112/assets/images/2025/MARCH/28/BXO0Hivc_009059fff7e742359d7ca8dcbfe539cb.jpg",
          "alt": "",
          "thumbnail": "https://assets.myntassets.com/f_auto,h_150,q_auto:best,w_112/assets/images/2025/MARCH/28/BXO0Hivc_009059fff7e742359d7ca8dcbfe539cb.jpg"
        },
        {
          "url": "https://constant.myntassets.com/web/assets/img/chevron-right.svg",
          "alt": "",
          "thumbnail": "https://constant.myntassets.com/web/assets/img/chevron-right.svg"
        }
      ],
      "description": "Kappa\nMen Navy Blue Colourblocked Synthetic Sliders\n4.2\n|\n29 Ratings\n₹1156\nMRP ₹1299(11% OFF)\ninclusive of all taxes\nMORE COLORS\nSELECT SIZE (UK Size)SIZE CHART\n6\nRs. 1156\n7\n8\nRs. 1169\n9\nRs. 1156\n2 left\n10\nRs. 1169\n11\nRs. 1156\n4 left\nADD TO BAG\nWISHLIST\nDELIVERY OPTIONS\nPlease enter PIN code to check delivery time & Pay on Delivery Availability\n100% Original Products\nPay on delivery might be available\nEasy 7 days returns and exchanges\nBEST OFFERS\nBest Price: Rs. 856\nApplicable on: Orders above Rs. 499 (only on first purchase)\nCoupon code: MYNTRAWOWZ\nCoupon Discount: 35% off (Your total saving: Rs. 443)\nView Eligible Products\n10% Discount on HDFC Bank Credit Card.\nMin Spend ₹750, Max Discount ₹3,500.\nTerms & Condition\n10% Discount on HDFC Bank Credit Card.\nMin Spend ₹1,000, Max Discount ₹3,500.\nTerms & Condition\n10% Discount on HDFC Bank Credit Card EMI.\nMin Spend ₹1,000, Max Discount ₹3,500.\nTerms & Condition\n10% Discount on HDFC Bank Debit Card EMI.\nMin Spend ₹1,000, Max Discount ₹3,500.\nTerms & Condition\nCustomers will receive Rs 250 voucher on a minimum spends of Rs 4,000 made via HDFC Bank NetBanking during Myntra’s BFF sale.\nMin Spend ₹4,000\nTerms & Condition\n7.5% Assured Cashback on Flipkart Axis Bank Credit Card.\nMaximum cashback: INR 4,000 per quarter ; Cashback is not applicable on transactions less than INR 100\nTerms & Condition\n7.5% Assured Cashback on Flipkart SBI Credit Card.\nMaximum cashback: INR 4,000 per quarter ; Cashback is not applicable on transactions less than INR 100\nTerms & Condition\nPRODUCT DETAILS\nA pair of Navy blue and orange colourblocked sliders\nSynthetic upper\nCushioned footbed\nPatterned synthetic outsole\nMaterial & Care\nUpper Material :  Synthetic\nSole Material :  Synthetic\nWipe with a clean, dry cloth to remove dust\nSpecifications\nMaterials\nSynthetic\nNet Quantity Unit\nPieces\nOccasions\nCasual\nPatterns\nColourblocked\nSole Material\nSynthetic\nSustainable\nRegular\nType\nSliders\nRATINGS\n4.2\n29 Verified Buyers\n5\n20\n4\n3\n3\n2\n3\n1\n3\nCustomer Photos (8)\nCustomer Reviews (15)\n5\nThese slides are really good, I've chosen them after a lot of mindless scrolling looking for products and price comparison. These feel like walking on clouds. Good grip and quite comfortable. It comes with a velcro strap for minor adjustments. 100% go for it.\nSafwan13 Sept 2025\n00\n5\nComfortable and stylish, great quality for the price!!\nMyntra Customer8 Apr 2025\n30\n5\nComfort is top level. And very good looking.\nAnkit Verma12 May 2025\n00\nView all 15 reviews\nProduct Code: 33376679\nSeller: LANDMARK ONLINE INDIA PVT LTD\nView Supplier Information",
      "specifications": {
        "Kappa\nMen Navy Blue Colourblocked Synthetic Sliders\n4.2\n|\n29 Ratings\n₹1156\nMRP ₹1299(11% OFF)\ninclusive of all taxes\nMORE COLORS\nSELECT SIZE (UK Size)SIZE CHART\n6\nRs. 1156\n7\n8\nRs. 1169\n9\nRs. 1156\n2 left\n10\nRs. 1169\n11\nRs. 1156\n4 left\nADD TO BAG\nWISHLIST\nDELIVERY OPTIONS\nPlease enter PIN code to check delivery time & Pay on Delivery Availability\n100% Original Products\nPay on delivery might be available\nEasy 7 days returns and exchanges\nBEST OFFERS\nBest Price": "Rs. 856\nApplicable on: Orders above Rs. 499 (only on first purchase)\nCoupon code: MYNTRAWOWZ\nCoupon Discount: 35% off (Your total saving: Rs. 443)\nView Eligible Products\n10% Discount on HDFC Bank Credit Card.\nMin Spend ₹750, Max Discount ₹3,500.\nTerms & Condition\n10% Discount on HDFC Bank Credit Card.\nMin Spend ₹1,000, Max Discount ₹3,500.\nTerms & Condition\n10% Discount on HDFC Bank Credit Card EMI.\nMin Spend ₹1,000, Max Discount ₹3,500.\nTerms & Condition\n10% Discount on HDFC Bank Debit Card EMI.\nMin Spend ₹1,000, Max Discount ₹3,500.\nTerms & Condition\nCustomers will receive Rs 250 voucher on a minimum spends of Rs 4,000 made via HDFC Bank NetBanking during Myntra’s BFF sale.\nMin Spend ₹4,000\nTerms & Condition\n7.5% Assured Cashback on Flipkart Axis Bank Credit Card.\nMaximum cashback: INR 4,000 per quarter ; Cashback is not applicable on transactions less than INR 100\nTerms & Condition\n7.5% Assured Cashback on Flipkart SBI Credit Card.\nMaximum cashback: INR 4,000 per quarter ; Cashback is not applicable on transactions less than INR 100\nTerms & Condition\nPRODUCT DETAILS\nA pair of Navy blue and orange colourblocked sliders\nSynthetic upper\nCushioned footbed\nPatterned synthetic outsole\nMaterial & Care\nUpper Material :  Synthetic\nSole Material :  Synthetic\nWipe with a clean, dry cloth to remove dust\nSpecifications\nMaterials\nSynthetic\nNet Quantity Unit\nPieces\nOccasions\nCasual\nPatterns\nColourblocked\nSole Material\nSynthetic\nSustainable\nRegular\nType\nSliders\nRATINGS\n4.2\n29 Verified Buyers\n5\n20\n4\n3\n3\n2\n3\n1\n3\nCustomer Photos (8)\nCustomer Reviews (15)\n5\nThese slides are really good, I've chosen them after a lot of mindless scrolling looking for products and price comparison. These feel like walking on clouds. Good grip and quite comfortable. It comes with a velcro strap for minor adjustments. 100% go for it.\nSafwan13 Sept 2025\n00\n5\nComfortable and stylish, great quality for the price!!\nMyntra Customer8 Apr 2025\n30\n5\nComfort is top level. And very good looking.\nAnkit Verma12 May 2025\n00\nView all 15 reviews\nProduct Code: 33376679\nSeller: LANDMARK ONLINE INDIA PVT LTD\nView Supplier Information",
        "MORE COLORS\nSELECT SIZE (UK Size)SIZE CHART\n6\nRs. 1156\n7\n8\nRs. 1169\n9\nRs. 1156\n2 left\n10\nRs. 1169\n11\nRs. 1156\n4 left\nADD TO BAG\nWISHLIST\nDELIVERY OPTIONS\nPlease enter PIN code to check delivery time & Pay on Delivery Availability\n100% Original Products\nPay on delivery might be available\nEasy 7 days returns and exchanges\nBEST OFFERS\nBest Price": "Rs. 856\nApplicable on: Orders above Rs. 499 (only on first purchase)\nCoupon code: MYNTRAWOWZ\nCoupon Discount: 35% off (Your total saving: Rs. 443)\nView Eligible Products\n10% Discount on HDFC Bank Credit Card.\nMin Spend ₹750, Max Discount ₹3,500.\nTerms & Condition\n10% Discount on HDFC Bank Credit Card.\nMin Spend ₹1,000, Max Discount ₹3,500.\nTerms & Condition\n10% Discount on HDFC Bank Credit Card EMI.\nMin Spend ₹1,000, Max Discount ₹3,500.\nTerms & Condition\n10% Discount on HDFC Bank Debit Card EMI.\nMin Spend ₹1,000, Max Discount ₹3,500.\nTerms & Condition\nCustomers will receive Rs 250 voucher on a minimum spends of Rs 4,000 made via HDFC Bank NetBanking during Myntra’s BFF sale.\nMin Spend ₹4,000\nTerms & Condition\n7.5% Assured Cashback on Flipkart Axis Bank Credit Card.\nMaximum cashback: INR 4,000 per quarter ; Cashback is not applicable on transactions less than INR 100\nTerms & Condition\n7.5% Assured Cashback on Flipkart SBI Credit Card.\nMaximum cashback: INR 4,000 per quarter ; Cashback is not applicable on transactions less than INR 100\nTerms & Condition",
        "BEST OFFERS\nBest Price": "Rs. 856\nApplicable on: Orders above Rs. 499 (only on first purchase)\nCoupon code: MYNTRAWOWZ\nCoupon Discount: 35% off (Your total saving: Rs. 443)\nView Eligible Products\n10% Discount on HDFC Bank Credit Card.\nMin Spend ₹750, Max Discount ₹3,500.\nTerms & Condition\n10% Discount on HDFC Bank Credit Card.\nMin Spend ₹1,000, Max Discount ₹3,500.\nTerms & Condition\n10% Discount on HDFC Bank Credit Card EMI.\nMin Spend ₹1,000, Max Discount ₹3,500.\nTerms & Condition\n10% Discount on HDFC Bank Debit Card EMI.\nMin Spend ₹1,000, Max Discount ₹3,500.\nTerms & Condition\nCustomers will receive Rs 250 voucher on a minimum spends of Rs 4,000 made via HDFC Bank NetBanking during Myntra’s BFF sale.\nMin Spend ₹4,000\nTerms & Condition\n7.5% Assured Cashback on Flipkart Axis Bank Credit Card.\nMaximum cashback: INR 4,000 per quarter ; Cashback is not applicable on transactions less than INR 100\nTerms & Condition\n7.5% Assured Cashback on Flipkart SBI Credit Card.\nMaximum cashback: INR 4,000 per quarter ; Cashback is not applicable on transactions less than INR 100\nTerms & Condition",
        "Best Price": "Rs. 856",
        "Applicable on": "Orders above Rs. 499 (only on first purchase)",
        "Coupon code": "MYNTRAWOWZ",
        "Coupon Discount": "35% off (Your total saving: Rs. 443)",
        "10% Discount on HDFC Bank Credit Card.\nMin Spend ₹750, Max Discount ₹3,500.\nTerms & Condition\n10% Discount on HDFC Bank Credit Card.\nMin Spend ₹1,000, Max Discount ₹3,500.\nTerms & Condition\n10% Discount on HDFC Bank Credit Card EMI.\nMin Spend ₹1,000, Max Discount ₹3,500.\nTerms & Condition\n10% Discount on HDFC Bank Debit Card EMI.\nMin Spend ₹1,000, Max Discount ₹3,500.\nTerms & Condition\nCustomers will receive Rs 250 voucher on a minimum spends of Rs 4,000 made via HDFC Bank NetBanking during Myntra’s BFF sale.\nMin Spend ₹4,000\nTerms & Condition\n7.5% Assured Cashback on Flipkart Axis Bank Credit Card.\nMaximum cashback": "INR 4,000 per quarter ; Cashback is not applicable on transactions less than INR 100\nTerms & Condition\n7.5% Assured Cashback on Flipkart SBI Credit Card.\nMaximum cashback: INR 4,000 per quarter ; Cashback is not applicable on transactions less than INR 100\nTerms & Condition",
        "7.5% Assured Cashback on Flipkart Axis Bank Credit Card.\nMaximum cashback": "INR 4,000 per quarter ; Cashback is not applicable on transactions less than INR 100\nTerms & Condition",
        "Maximum cashback": "INR 4,000 per quarter ; Cashback is not applicable on transactions less than INR 100",
        "7.5% Assured Cashback on Flipkart SBI Credit Card.\nMaximum cashback": "INR 4,000 per quarter ; Cashback is not applicable on transactions less than INR 100\nTerms & Condition",
        "PRODUCT DETAILS\nA pair of Navy blue and orange colourblocked sliders\nSynthetic upper\nCushioned footbed\nPatterned synthetic outsole\nMaterial & Care\nUpper Material": "Synthetic\nSole Material :  Synthetic\nWipe with a clean, dry cloth to remove dust\nSpecifications\nMaterials\nSynthetic\nNet Quantity Unit\nPieces\nOccasions\nCasual\nPatterns\nColourblocked\nSole Material\nSynthetic\nSustainable\nRegular\nType\nSliders",
        "Material & Care\nUpper Material": "Synthetic\nSole Material :  Synthetic\nWipe with a clean, dry cloth to remove dust",
        "Product Code": "33376679",
        "Seller": "LANDMARK ONLINE INDIA PVT LTD\nView Supplier Information"
      }
    },
    {
      "name": "HRX by Hrithik Roshan",
      "price": "₹657",
      "original_price": "MRP ₹2399",
      "discount": "(72% OFF)",
      "brand": "HRX",
      "category": "More By HRX By Hrithik Roshan",
      "rating": "4.4",
      "reviews_count": "",
      "size_options": [
        "5",
        "8",
        "4",
        "10",
        "11",
        "9",
        "6",
        "7"
      ],
      "color_options": [],
      "availability": "",
      "link": "https://www.myntra.com/flip-flops/hrx+by+hrithik+roshan/hrx-by-hrithik-roshan-unisex-printed-sliders/36064822/buy",
      "images": [
        {
          "url": "https://constant.myntassets.com/web/assets/img/chevron-right.svg",
          "alt": "",
          "thumbnail": "https://constant.myntassets.com/web/assets/img/chevron-right.svg"
        }
      ],
      "description": "HRX by Hrithik Roshan\nUnisex Printed Sliders\n₹657\nMRP ₹2399(72% OFF)\ninclusive of all taxes\nSELECT SIZE (UK Size)SIZE CHART\n4\n5\n6\n7\n8\n9\n10\n11\nADD TO BAG\nWISHLIST\nDELIVERY OPTIONS\nPlease enter PIN code to check delivery time & Pay on Delivery Availability\n100% Original Products\nPay on delivery might be available\nEasy 7 days returns and exchanges\nBEST OFFERS\nBest Price: Rs. 427\nApplicable on: Orders above Rs. 499 (only on first purchase)\nCoupon code: MYNTRAWOWZ\nCoupon Discount: 35% off (Your total saving: Rs. 1972)\nView Eligible Products\n10% Discount on HDFC Bank Credit Card.\nMin Spend ₹750, Max Discount ₹3,500.\nTerms & Condition\n10% Discount on HDFC Bank Credit Card.\nMin Spend ₹1,000, Max Discount ₹3,500.\nTerms & Condition\n10% Discount on HDFC Bank Credit Card EMI.\nMin Spend ₹1,000, Max Discount ₹3,500.\nTerms & Condition\n10% Discount on HDFC Bank Debit Card EMI.\nMin Spend ₹1,000, Max Discount ₹3,500.\nTerms & Condition\nCustomers will receive Rs 250 voucher on a minimum spends of Rs 4,000 made via HDFC Bank NetBanking during Myntra’s BFF sale.\nMin Spend ₹4,000\nTerms & Condition\n7.5% Assured Cashback on Flipkart Axis Bank Credit Card.\nMaximum cashback: INR 4,000 per quarter ; Cashback is not applicable on transactions less than INR 100\nTerms & Condition\n7.5% Assured Cashback on Flipkart SBI Credit Card.\nMaximum cashback: INR 4,000 per quarter ; Cashback is not applicable on transactions less than INR 100\nTerms & Condition\nPRODUCT DETAILS\nA pair of black printed sliders\nSynthetic upper\nCushioned footbed\nPatterned eva outsole\nWarranty: 14 days\nWarranty provided by brand owner/manufacturer\nMaterial & Care\nSynthetic\nWipe with a clean, dry cloth to remove dust.\nSpecifications\nMaterials\nSynthetic\nNet Quantity Unit\nPieces\nOccasions\nCasual\nPatterns\nPrinted\nSole Material\nEVA\nSustainable\nRegular\nType\nSliders\nWarranty\n14 days\nProduct Code: 36064822\nSeller: Gochums Private Limited\nView Supplier Information",
      "specifications": {
        "HRX by Hrithik Roshan\nUnisex Printed Sliders\n₹657\nMRP ₹2399(72% OFF)\ninclusive of all taxes\nSELECT SIZE (UK Size)SIZE CHART\n4\n5\n6\n7\n8\n9\n10\n11\nADD TO BAG\nWISHLIST\nDELIVERY OPTIONS\nPlease enter PIN code to check delivery time & Pay on Delivery Availability\n100% Original Products\nPay on delivery might be available\nEasy 7 days returns and exchanges\nBEST OFFERS\nBest Price": "Rs. 427\nApplicable on: Orders above Rs. 499 (only on first purchase)\nCoupon code: MYNTRAWOWZ\nCoupon Discount: 35% off (Your total saving: Rs. 1972)\nView Eligible Products\n10% Discount on HDFC Bank Credit Card.\nMin Spend ₹750, Max Discount ₹3,500.\nTerms & Condition\n10% Discount on HDFC Bank Credit Card.\nMin Spend ₹1,000, Max Discount ₹3,500.\nTerms & Condition\n10% Discount on HDFC Bank Credit Card EMI.\nMin Spend ₹1,000, Max Discount ₹3,500.\nTerms & Condition\n10% Discount on HDFC Bank Debit Card EMI.\nMin Spend ₹1,000, Max Discount ₹3,500.\nTerms & Condition\nCustomers will receive Rs 250 voucher on a minimum spends of Rs 4,000 made via HDFC Bank NetBanking during Myntra’s BFF sale.\nMin Spend ₹4,000\nTerms & Condition\n7.5% Assured Cashback on Flipkart Axis Bank Credit Card.\nMaximum cashback: INR 4,000 per quarter ; Cashback is not applicable on transactions less than INR 100\nTerms & Condition\n7.5% Assured Cashback on Flipkart SBI Credit Card.\nMaximum cashback: INR 4,000 per quarter ; Cashback is not applicable on transactions less than INR 100\nTerms & Condition\nPRODUCT DETAILS\nA pair of black printed sliders\nSynthetic upper\nCushioned footbed\nPatterned eva outsole\nWarranty: 14 days\nWarranty provided by brand owner/manufacturer\nMaterial & Care\nSynthetic\nWipe with a clean, dry cloth to remove dust.\nSpecifications\nMaterials\nSynthetic\nNet Quantity Unit\nPieces\nOccasions\nCasual\nPatterns\nPrinted\nSole Material\nEVA\nSustainable\nRegular\nType\nSliders\nWarranty\n14 days\nProduct Code: 36064822\nSeller: Gochums Private Limited\nView Supplier Information",
        "SELECT SIZE (UK Size)SIZE CHART\n4\n5\n6\n7\n8\n9\n10\n11\nADD TO BAG\nWISHLIST\nDELIVERY OPTIONS\nPlease enter PIN code to check delivery time & Pay on Delivery Availability\n100% Original Products\nPay on delivery might be available\nEasy 7 days returns and exchanges\nBEST OFFERS\nBest Price": "Rs. 427\nApplicable on: Orders above Rs. 499 (only on first purchase)\nCoupon code: MYNTRAWOWZ\nCoupon Discount: 35% off (Your total saving: Rs. 1972)\nView Eligible Products\n10% Discount on HDFC Bank Credit Card.\nMin Spend ₹750, Max Discount ₹3,500.\nTerms & Condition\n10% Discount on HDFC Bank Credit Card.\nMin Spend ₹1,000, Max Discount ₹3,500.\nTerms & Condition\n10% Discount on HDFC Bank Credit Card EMI.\nMin Spend ₹1,000, Max Discount ₹3,500.\nTerms & Condition\n10% Discount on HDFC Bank Debit Card EMI.\nMin Spend ₹1,000, Max Discount ₹3,500.\nTerms & Condition\nCustomers will receive Rs 250 voucher on a minimum spends of Rs 4,000 made via HDFC Bank NetBanking during Myntra’s BFF sale.\nMin Spend ₹4,000\nTerms & Condition\n7.5% Assured Cashback on Flipkart Axis Bank Credit Card.\nMaximum cashback: INR 4,000 per quarter ; Cashback is not applicable on transactions less than INR 100\nTerms & Condition\n7.5% Assured Cashback on Flipkart SBI Credit Card.\nMaximum cashback: INR 4,000 per quarter ; Cashback is not applicable on transactions less than INR 100\nTerms & Condition",
        "BEST OFFERS\nBest Price": "Rs. 427\nApplicable on: Orders above Rs. 499 (only on first purchase)\nCoupon code: MYNTRAWOWZ\nCoupon Discount: 35% off (Your total saving: Rs. 1972)\nView Eligible Products\n10% Discount on HDFC Bank Credit Card.\nMin Spend ₹750, Max Discount ₹3,500.\nTerms & Condition\n10% Discount on HDFC Bank Credit Card.\nMin Spend ₹1,000, Max Discount ₹3,500.\nTerms & Condition\n10% Discount on HDFC Bank Credit Card EMI.\nMin Spend ₹1,000, Max Discount ₹3,500.\nTerms & Condition\n10% Discount on HDFC Bank Debit Card EMI.\nMin Spend ₹1,000, Max Discount ₹3,500.\nTerms & Condition\nCustomers will receive Rs 250 voucher on a minimum spends of Rs 4,000 made via HDFC Bank NetBanking during Myntra’s BFF sale.\nMin Spend ₹4,000\nTerms & Condition\n7.5% Assured Cashback on Flipkart Axis Bank Credit Card.\nMaximum cashback: INR 4,000 per quarter ; Cashback is not applicable on transactions less than INR 100\nTerms & Condition\n7.5% Assured Cashback on Flipkart SBI Credit Card.\nMaximum cashback: INR 4,000 per quarter ; Cashback is not applicable on transactions less than INR 100\nTerms & Condition",
        "Best Price": "Rs. 427",
        "Applicable on": "Orders above Rs. 499 (only on first purchase)",
        "Coupon code": "MYNTRAWOWZ",
        "Coupon Discount": "35% off (Your total saving: Rs. 1972)",
        "10% Discount on HDFC Bank Credit Card.\nMin Spend ₹750, Max Discount ₹3,500.\nTerms & Condition\n10% Discount on HDFC Bank Credit Card.\nMin Spend ₹1,000, Max Discount ₹3,500.\nTerms & Condition\n10% Discount on HDFC Bank Credit Card EMI.\nMin Spend ₹1,000, Max Discount ₹3,500.\nTerms & Condition\n10% Discount on HDFC Bank Debit Card EMI.\nMin Spend ₹1,000, Max Discount ₹3,500.\nTerms & Condition\nCustomers will receive Rs 250 voucher on a minimum spends of Rs 4,000 made via HDFC Bank NetBanking during Myntra’s BFF sale.\nMin Spend ₹4,000\nTerms & Condition\n7.5% Assured Cashback on Flipkart Axis Bank Credit Card.\nMaximum cashback": "INR 4,000 per quarter ; Cashback is not applicable on transactions less than INR 100\nTerms & Condition\n7.5% Assured Cashback on Flipkart SBI Credit Card.\nMaximum cashback: INR 4,000 per quarter ; Cashback is not applicable on transactions less than INR 100\nTerms & Condition",
        "7.5% Assured Cashback on Flipkart Axis Bank Credit Card.\nMaximum cashback": "INR 4,000 per quarter ; Cashback is not applicable on transactions less than INR 100\nTerms & Condition",
        "Maximum cashback": "INR 4,000 per quarter ; Cashback is not applicable on transactions less than INR 100",
        "7.5% Assured Cashback on Flipkart SBI Credit Card.\nMaximum cashback": "INR 4,000 per quarter ; Cashback is not applicable on transactions less than INR 100\nTerms & Condition",
        "PRODUCT DETAILS\nA pair of black printed sliders\nSynthetic upper\nCushioned footbed\nPatterned eva outsole\nWarranty": "14 days\nWarranty provided by brand owner/manufacturer",
        "Product Code": "36064822",
        "Seller": "Gochums Private Limited\nView Supplier Information"
      }
    }
  ]
}